excel_scraper/__init__.py
excel_scraper/main.py
excel_scraper/scraper.py
nyc_infohub_excel_api_access-1.0.15.dist-info/LICENSE
nyc_infohub_excel_api_access-1.0.15.dist-info/METADATA
nyc_infohub_excel_api_access-1.0.15.dist-info/WHEEL
nyc_infohub_excel_api_access-1.0.15.dist-info/entry_points.txt
nyc_infohub_excel_api_access-1.0.15.dist-info/top_level.txt
nyc_infohub_excel_api_access-1.0.15.dist-info/RECORD
