Metadata-Version: 2.2
Name: nyc_infohub_excel_api_access
Version: 1.0.15
Summary: A Python scraper for downloading Excel datasets from NYC InfoHub.
Home-page: https://github.com/dylanpicart/excel_api_access
Author: Dylan Picart
Author-email: dylanpicart@mail.adelphi.edu
Classifier: Programming Language :: Python :: 3
Classifier: License :: OSI Approved :: MIT License
Classifier: Operating System :: OS Independent
Requires-Python: >=3.8
License-File: LICENSE
Requires-Dist: httpx[http2]>=0.28.1
Requires-Dist: tenacity>=8.0.1
Requires-Dist: pyclamd
Requires-Dist: clamd
Requires-Dist: python-magic
Requires-Dist: selenium>=4.10.0
Requires-Dist: pandas>=1.3.0
Requires-Dist: tqdm>=4.62.0
Requires-Dist: openpyxl>=3.0.9
Requires-Dist: pyxlsb>=1.0.10
Requires-Dist: xlrd>=2.0.1
Requires-Dist: python-dotenv>=1.0.0
Requires-Dist: pytest<8.0,>=7.0
Requires-Dist: pytest-asyncio
Requires-Dist: pytest-cov
Dynamic: author
Dynamic: author-email
Dynamic: classifier
Dynamic: description
Dynamic: description-content-type
Dynamic: home-page
Dynamic: requires-dist
Dynamic: requires-python
Dynamic: summary
